<?xml version="1.0" encoding="UTF-8"?>
<!DOCTYPE score-partwise PUBLIC "-//Recordare//DTD MusicXML 3.0 Partwise//EN" "http://www.musicxml.org/dtds/partwise.dtd">
<score-partwise>
  <movement-title>Brown girl in the ring</movement-title>
  <identification>
    <encoding>
      <software>MuseScore 2.0.2</software>
      <encoding-date>2016-01-10</encoding-date>
      <supports element="accidental" type="yes"/>
      <supports element="beam" type="yes"/>
      <supports element="print" attribute="new-page" type="yes" value="yes"/>
      <supports element="print" attribute="new-system" type="yes" value="yes"/>
      <supports element="stem" type="yes"/>
      </encoding>
    <source>http://wikifonia.org/node/746/revisions/1078/view</source>
    </identification>
  <defaults>
    <scaling>
      <millimeters>7.23192</millimeters>
      <tenths>40</tenths>
      </scaling>
    <page-layout>
      <page-height>1545.37</page-height>
      <page-width>1194.15</page-width>
      <page-margins type="both">
        <left-margin>69.9998</left-margin>
        <right-margin>69.9998</right-margin>
        <top-margin>87.9997</top-margin>
        <bottom-margin>87.9997</bottom-margin>
        </page-margins>
      </page-layout>
    <word-font font-family="FreeSerif" font-size="10"/>
    <lyric-font font-family="FreeSerif" font-size="11"/>
    </defaults>
  <credit page="1">
    <credit-words default-x="597.075" default-y="1457.37" justify="center" valign="top" font-family="Times New Roman" font-size="24">Brown girl in the ring
</credit-words>
    </credit>
  <credit page="1">
    <credit-words default-x="1124.15" default-y="1357.37" justify="right" valign="bottom" font-family="Times New Roman" font-size="12">Boney M</credit-words>
    </credit>
  <part-list>
    <score-part id="P1">
      <part-name></part-name>
      <score-instrument id="P1-I1">
        <instrument-name></instrument-name>
        </score-instrument>
      <midi-device id="P1-I1" port="1"></midi-device>
      <midi-instrument id="P1-I1">
        <midi-channel>1</midi-channel>
        <midi-program>1</midi-program>
        <volume>78.7402</volume>
        <pan>0</pan>
        </midi-instrument>
      </score-part>
    </part-list>
  <part id="P1">
    <measure number="1" width="327.74">
      <print>
        <system-layout>
          <system-margins>
            <left-margin>0.00</left-margin>
            <right-margin>0.00</right-margin>
            </system-margins>
          <top-system-distance>180.00</top-system-distance>
          </system-layout>
        </print>
      <attributes>
        <divisions>4</divisions>
        <key>
          <fifths>0</fifths>
          </key>
        <time symbol="common">
          <beats>4</beats>
          <beat-type>4</beat-type>
          </time>
        <clef>
          <sign>G</sign>
          <line>2</line>
          </clef>
        </attributes>
      <harmony print-frame="no">
        <root>
          <root-step>C</root-step>
          </root>
        <kind>major</kind>
        </harmony>
      <note default-x="97.14" default-y="-40.00">
        <pitch>
          <step>E</step>
          <octave>4</octave>
          </pitch>
        <duration>4</duration>
        <voice>1</voice>
        <type>quarter</type>
        <stem>up</stem>
        <lyric number="1">
          <syllabic>single</syllabic>
          <text font-family="Times New Roman" font-size="10.7317">Brown</text>
          </lyric>
        </note>
      <note default-x="144.49" default-y="-40.00">
        <pitch>
          <step>E</step>
          <octave>4</octave>
          </pitch>
        <duration>4</duration>
        <voice>1</voice>
        <type>quarter</type>
        <stem>up</stem>
        <lyric number="1">
          <syllabic>single</syllabic>
          <text font-family="Times New Roman" font-size="10.7317">girl</text>
          </lyric>
        </note>
      <note default-x="183.70" default-y="-40.00">
        <pitch>
          <step>E</step>
          <octave>4</octave>
          </pitch>
        <duration>2</duration>
        <voice>1</voice>
        <type>eighth</type>
        <stem>up</stem>
        <beam number="1">begin</beam>
        <lyric number="1">
          <syllabic>single</syllabic>
          <text font-family="Times New Roman" font-size="10.7317">in</text>
          </lyric>
        </note>
      <note default-x="212.22" default-y="-45.00">
        <pitch>
          <step>D</step>
          <octave>4</octave>
          </pitch>
        <duration>1</duration>
        <voice>1</voice>
        <type>16th</type>
        <stem>up</stem>
        <beam number="1">continue</beam>
        <beam number="2">begin</beam>
        <lyric number="1">
          <syllabic>single</syllabic>
          <text font-family="Times New Roman" font-size="10.7317">the</text>
          </lyric>
        </note>
      <note default-x="246.62" default-y="-50.00">
        <pitch>
          <step>C</step>
          <octave>4</octave>
          </pitch>
        <duration>1</duration>
        <tie type="start"/>
        <voice>1</voice>
        <type>16th</type>
        <stem>up</stem>
        <beam number="1">end</beam>
        <beam number="2">end</beam>
        <notations>
          <tied type="start"/>
          </notations>
        <lyric number="1">
          <syllabic>single</syllabic>
          <text font-family="Times New Roman" font-size="10.7317">ring,</text>
          </lyric>
        </note>
      <note default-x="286.93" default-y="-50.00">
        <pitch>
          <step>C</step>
          <octave>4</octave>
          </pitch>
        <duration>4</duration>
        <tie type="stop"/>
        <voice>1</voice>
        <type>quarter</type>
        <stem>up</stem>
        <notations>
          <tied type="stop"/>
          </notations>
        </note>
      </measure>
    <measure number="2" width="268.30">
      <note default-x="16.54" default-y="-40.00">
        <pitch>
          <step>E</step>
          <octave>4</octave>
          </pitch>
        <duration>3</duration>
        <voice>1</voice>
        <type>eighth</type>
        <dot/>
        <stem>up</stem>
        <beam number="1">begin</beam>
        <lyric number="1">
          <syllabic>begin</syllabic>
          <text font-family="Times New Roman" font-size="10.7317">tra</text>
          </lyric>
        </note>
      <note default-x="56.61" default-y="-45.00">
        <pitch>
          <step>D</step>
          <octave>4</octave>
          </pitch>
        <duration>1</duration>
        <voice>1</voice>
        <type>16th</type>
        <stem>up</stem>
        <beam number="1">end</beam>
        <beam number="2">backward hook</beam>
        <lyric number="1">
          <syllabic>middle</syllabic>
          <text font-family="Times New Roman" font-size="10.7317">la</text>
          </lyric>
        </note>
      <note default-x="77.14" default-y="-40.00">
        <pitch>
          <step>E</step>
          <octave>4</octave>
          </pitch>
        <duration>3</duration>
        <voice>1</voice>
        <type>eighth</type>
        <dot/>
        <stem>up</stem>
        <beam number="1">begin</beam>
        <lyric number="1">
          <syllabic>middle</syllabic>
          <text font-family="Times New Roman" font-size="10.7317">la</text>
          </lyric>
        </note>
      <note default-x="117.21" default-y="-35.00">
        <pitch>
          <step>F</step>
          <octave>4</octave>
          </pitch>
        <duration>1</duration>
        <voice>1</voice>
        <type>16th</type>
        <stem>up</stem>
        <beam number="1">end</beam>
        <beam number="2">backward hook</beam>
        <lyric number="1">
          <syllabic>middle</syllabic>
          <text font-family="Times New Roman" font-size="10.7317">la</text>
          </lyric>
        </note>
      <note default-x="137.74" default-y="-30.00">
        <pitch>
          <step>G</step>
          <octave>4</octave>
          </pitch>
        <duration>4</duration>
        <voice>1</voice>
        <type>quarter</type>
        <stem>up</stem>
        <lyric number="1">
          <syllabic>end</syllabic>
          <text font-family="Times New Roman" font-size="10.7317">la,</text>
          </lyric>
        </note>
      <note default-x="184.69" default-y="-50.00">
        <pitch>
          <step>C</step>
          <octave>4</octave>
          </pitch>
        <duration>2</duration>
        <voice>1</voice>
        <type>eighth</type>
        <stem>up</stem>
        <beam number="1">begin</beam>
        <lyric number="1">
          <syllabic>single</syllabic>
          <text font-family="Times New Roman" font-size="10.7317">There's</text>
          </lyric>
        </note>
      <note default-x="233.85" default-y="-50.00">
        <pitch>
          <step>C</step>
          <octave>4</octave>
          </pitch>
        <duration>2</duration>
        <voice>1</voice>
        <type>eighth</type>
        <stem>up</stem>
        <beam number="1">end</beam>
        <lyric number="1">
          <syllabic>single</syllabic>
          <text font-family="Times New Roman" font-size="10.7317">a</text>
          </lyric>
        </note>
      </measure>
    <measure number="3" width="261.22">
      <harmony print-frame="no">
        <root>
          <root-step>G</root-step>
          </root>
        <kind>major</kind>
        </harmony>
      <note default-x="32.38" default-y="-45.00">
        <pitch>
          <step>D</step>
          <octave>4</octave>
          </pitch>
        <duration>4</duration>
        <voice>1</voice>
        <type>quarter</type>
        <stem>up</stem>
        <lyric number="1">
          <syllabic>single</syllabic>
          <text font-family="Times New Roman" font-size="10.7317">brown</text>
          </lyric>
        </note>
      <note default-x="77.97" default-y="-45.00">
        <pitch>
          <step>D</step>
          <octave>4</octave>
          </pitch>
        <duration>4</duration>
        <voice>1</voice>
        <type>quarter</type>
        <stem>up</stem>
        <lyric number="1">
          <syllabic>single</syllabic>
          <text font-family="Times New Roman" font-size="10.7317">girl</text>
          </lyric>
        </note>
      <note default-x="117.18" default-y="-45.00">
        <pitch>
          <step>D</step>
          <octave>4</octave>
          </pitch>
        <duration>2</duration>
        <voice>1</voice>
        <type>eighth</type>
        <stem>up</stem>
        <beam number="1">begin</beam>
        <lyric number="1">
          <syllabic>single</syllabic>
          <text font-family="Times New Roman" font-size="10.7317">in</text>
          </lyric>
        </note>
      <note default-x="145.70" default-y="-50.00">
        <pitch>
          <step>C</step>
          <octave>4</octave>
          </pitch>
        <duration>1</duration>
        <voice>1</voice>
        <type>16th</type>
        <stem>up</stem>
        <beam number="1">continue</beam>
        <beam number="2">begin</beam>
        <lyric number="1">
          <syllabic>single</syllabic>
          <text font-family="Times New Roman" font-size="10.7317">the</text>
          </lyric>
        </note>
      <note default-x="180.10" default-y="-55.00">
        <pitch>
          <step>B</step>
          <octave>3</octave>
          </pitch>
        <duration>1</duration>
        <tie type="start"/>
        <voice>1</voice>
        <type>16th</type>
        <stem>up</stem>
        <beam number="1">end</beam>
        <beam number="2">end</beam>
        <notations>
          <tied type="start"/>
          </notations>
        <lyric number="1">
          <syllabic>single</syllabic>
          <text font-family="Times New Roman" font-size="10.7317">ring,</text>
          </lyric>
        </note>
      <note default-x="220.41" default-y="-55.00">
        <pitch>
          <step>B</step>
          <octave>3</octave>
          </pitch>
        <duration>4</duration>
        <tie type="stop"/>
        <voice>1</voice>
        <type>quarter</type>
        <stem>up</stem>
        <notations>
          <tied type="stop"/>
          </notations>
        </note>
      </measure>
    <measure number="4" width="196.88">
      <note default-x="16.54" default-y="-30.00">
        <pitch>
          <step>G</step>
          <octave>4</octave>
          </pitch>
        <duration>6</duration>
        <voice>1</voice>
        <type>quarter</type>
        <dot/>
        <stem>up</stem>
        <lyric number="1">
          <syllabic>begin</syllabic>
          <text font-family="Times New Roman" font-size="10.7317">tra</text>
          </lyric>
        </note>
      <note default-x="64.62" default-y="-25.00">
        <pitch>
          <step>A</step>
          <octave>4</octave>
          </pitch>
        <duration>2</duration>
        <voice>1</voice>
        <type>eighth</type>
        <stem>up</stem>
        <lyric number="1">
          <syllabic>middle</syllabic>
          <text font-family="Times New Roman" font-size="10.7317">la</text>
          </lyric>
        </note>
      <note default-x="92.42" default-y="-30.00">
        <pitch>
          <step>G</step>
          <octave>4</octave>
          </pitch>
        <duration>2</duration>
        <voice>1</voice>
        <type>eighth</type>
        <stem>up</stem>
        <beam number="1">begin</beam>
        <lyric number="1">
          <syllabic>middle</syllabic>
          <text font-family="Times New Roman" font-size="10.7317">la</text>
          </lyric>
        </note>
      <note default-x="117.06" default-y="-35.00">
        <pitch>
          <step>F</step>
          <octave>4</octave>
          </pitch>
        <duration>2</duration>
        <voice>1</voice>
        <type>eighth</type>
        <stem>up</stem>
        <beam number="1">continue</beam>
        <lyric number="1">
          <syllabic>middle</syllabic>
          <text font-family="Times New Roman" font-size="10.7317">la</text>
          </lyric>
        </note>
      <note default-x="141.71" default-y="-40.00">
        <pitch>
          <step>E</step>
          <octave>4</octave>
          </pitch>
        <duration>2</duration>
        <voice>1</voice>
        <type>eighth</type>
        <stem>up</stem>
        <beam number="1">continue</beam>
        <lyric number="1">
          <syllabic>middle</syllabic>
          <text font-family="Times New Roman" font-size="10.7317">la</text>
          </lyric>
        </note>
      <note default-x="166.35" default-y="-45.00">
        <pitch>
          <step>D</step>
          <octave>4</octave>
          </pitch>
        <duration>2</duration>
        <voice>1</voice>
        <type>eighth</type>
        <stem>up</stem>
        <beam number="1">end</beam>
        <lyric number="1">
          <syllabic>end</syllabic>
          <text font-family="Times New Roman" font-size="10.7317">la,</text>
          </lyric>
        </note>
      </measure>
    <measure number="5" width="313.48">
      <print new-system="yes">
        <system-layout>
          <system-margins>
            <left-margin>0.00</left-margin>
            <right-margin>0.00</right-margin>
            </system-margins>
          <system-distance>150.00</system-distance>
          </system-layout>
        </print>
      <harmony print-frame="no">
        <root>
          <root-step>C</root-step>
          </root>
        <kind>major</kind>
        </harmony>
      <note default-x="69.85" default-y="-40.00">
        <pitch>
          <step>E</step>
          <octave>4</octave>
          </pitch>
        <duration>4</duration>
        <voice>1</voice>
        <type>quarter</type>
        <stem>up</stem>
        <lyric number="1">
          <syllabic>single</syllabic>
          <text font-family="Times New Roman" font-size="10.7317">Brown</text>
          </lyric>
        </note>
      <note default-x="117.20" default-y="-40.00">
        <pitch>
          <step>E</step>
          <octave>4</octave>
          </pitch>
        <duration>4</duration>
        <voice>1</voice>
        <type>quarter</type>
        <stem>up</stem>
        <lyric number="1">
          <syllabic>single</syllabic>
          <text font-family="Times New Roman" font-size="10.7317">girl</text>
          </lyric>
        </note>
      <note default-x="161.19" default-y="-40.00">
        <pitch>
          <step>E</step>
          <octave>4</octave>
          </pitch>
        <duration>2</duration>
        <voice>1</voice>
        <type>eighth</type>
        <stem>up</stem>
        <beam number="1">begin</beam>
        <lyric number="1">
          <syllabic>single</syllabic>
          <text font-family="Times New Roman" font-size="10.7317">in</text>
          </lyric>
        </note>
      <note default-x="193.18" default-y="-45.00">
        <pitch>
          <step>D</step>
          <octave>4</octave>
          </pitch>
        <duration>1</duration>
        <voice>1</voice>
        <type>16th</type>
        <stem>up</stem>
        <beam number="1">continue</beam>
        <beam number="2">begin</beam>
        <lyric number="1">
          <syllabic>single</syllabic>
          <text font-family="Times New Roman" font-size="10.7317">the</text>
          </lyric>
        </note>
      <note default-x="227.58" default-y="-50.00">
        <pitch>
          <step>C</step>
          <octave>4</octave>
          </pitch>
        <duration>1</duration>
        <tie type="start"/>
        <voice>1</voice>
        <type>16th</type>
        <stem>up</stem>
        <beam number="1">end</beam>
        <beam number="2">end</beam>
        <notations>
          <tied type="start"/>
          </notations>
        <lyric number="1">
          <syllabic>single</syllabic>
          <text font-family="Times New Roman" font-size="10.7317">ring,</text>
          </lyric>
        </note>
      <note default-x="267.89" default-y="-50.00">
        <pitch>
          <step>C</step>
          <octave>4</octave>
          </pitch>
        <duration>4</duration>
        <tie type="stop"/>
        <voice>1</voice>
        <type>quarter</type>
        <stem>up</stem>
        <notations>
          <tied type="stop"/>
          </notations>
        </note>
      </measure>
    <measure number="6" width="224.59">
      <note default-x="16.54" default-y="-40.00">
        <pitch>
          <step>E</step>
          <octave>4</octave>
          </pitch>
        <duration>3</duration>
        <voice>1</voice>
        <type>eighth</type>
        <dot/>
        <stem>up</stem>
        <beam number="1">begin</beam>
        <lyric number="1">
          <syllabic>begin</syllabic>
          <text font-family="Times New Roman" font-size="10.7317">tra</text>
          </lyric>
        </note>
      <note default-x="52.98" default-y="-45.00">
        <pitch>
          <step>D</step>
          <octave>4</octave>
          </pitch>
        <duration>1</duration>
        <voice>1</voice>
        <type>16th</type>
        <stem>up</stem>
        <beam number="1">end</beam>
        <beam number="2">backward hook</beam>
        <lyric number="1">
          <syllabic>middle</syllabic>
          <text font-family="Times New Roman" font-size="10.7317">la</text>
          </lyric>
        </note>
      <note default-x="72.19" default-y="-40.00">
        <pitch>
          <step>E</step>
          <octave>4</octave>
          </pitch>
        <duration>3</duration>
        <voice>1</voice>
        <type>eighth</type>
        <dot/>
        <stem>up</stem>
        <beam number="1">begin</beam>
        <lyric number="1">
          <syllabic>middle</syllabic>
          <text font-family="Times New Roman" font-size="10.7317">la</text>
          </lyric>
        </note>
      <note default-x="108.63" default-y="-35.00">
        <pitch>
          <step>F</step>
          <octave>4</octave>
          </pitch>
        <duration>1</duration>
        <voice>1</voice>
        <type>16th</type>
        <stem>up</stem>
        <beam number="1">end</beam>
        <beam number="2">backward hook</beam>
        <lyric number="1">
          <syllabic>end</syllabic>
          <text font-family="Times New Roman" font-size="10.7317">la.</text>
          </lyric>
        </note>
      <note default-x="140.81" default-y="-30.00">
        <pitch>
          <step>G</step>
          <octave>4</octave>
          </pitch>
        <duration>4</duration>
        <voice>1</voice>
        <type>quarter</type>
        <stem>up</stem>
        <lyric number="1">
          <syllabic>single</syllabic>
          <text font-family="Times New Roman" font-size="10.7317">She</text>
          </lyric>
        </note>
      <note default-x="181.90" default-y="-30.00">
        <pitch>
          <step>G</step>
          <octave>4</octave>
          </pitch>
        <duration>4</duration>
        <voice>1</voice>
        <type>quarter</type>
        <stem>up</stem>
        </note>
      </measure>
    <measure number="7" width="258.22">
      <harmony print-frame="no">
        <root>
          <root-step>C</root-step>
          </root>
        <kind>major</kind>
        </harmony>
      <note default-x="28.28" default-y="-15.00">
        <pitch>
          <step>C</step>
          <octave>5</octave>
          </pitch>
        <duration>4</duration>
        <voice>1</voice>
        <type>quarter</type>
        <stem>down</stem>
        <lyric number="1">
          <syllabic>single</syllabic>
          <text font-family="Times New Roman" font-size="10.7317">looks</text>
          </lyric>
        </note>
      <note default-x="76.35" default-y="-30.00">
        <pitch>
          <step>G</step>
          <octave>4</octave>
          </pitch>
        <duration>2</duration>
        <voice>1</voice>
        <type>eighth</type>
        <stem>up</stem>
        <beam number="1">begin</beam>
        <lyric number="1">
          <syllabic>single</syllabic>
          <text font-family="Times New Roman" font-size="10.7317">like</text>
          </lyric>
        </note>
      <note default-x="106.40" default-y="-30.00">
        <pitch>
          <step>G</step>
          <octave>4</octave>
          </pitch>
        <duration>2</duration>
        <voice>1</voice>
        <type>eighth</type>
        <stem>up</stem>
        <beam number="1">end</beam>
        <lyric number="1">
          <syllabic>single</syllabic>
          <text font-family="Times New Roman" font-size="10.7317">a</text>
          </lyric>
        </note>
      <note default-x="136.44" default-y="-40.00">
        <pitch>
          <step>E</step>
          <octave>4</octave>
          </pitch>
        <duration>2</duration>
        <voice>1</voice>
        <type>eighth</type>
        <stem>up</stem>
        <beam number="1">begin</beam>
        <lyric number="1">
          <syllabic>begin</syllabic>
          <text font-family="Times New Roman" font-size="10.7317">su</text>
          </lyric>
        </note>
      <note default-x="166.49" default-y="-40.00">
        <pitch>
          <step>E</step>
          <octave>4</octave>
          </pitch>
        <duration>2</duration>
        <voice>1</voice>
        <type>eighth</type>
        <stem>up</stem>
        <beam number="1">continue</beam>
        <lyric number="1">
          <syllabic>end</syllabic>
          <text font-family="Times New Roman" font-size="10.7317">gar</text>
          </lyric>
        </note>
      <harmony print-frame="no">
        <root>
          <root-step>G</root-step>
          </root>
        <kind>major</kind>
        </harmony>
      <note default-x="196.53" default-y="-45.00">
        <pitch>
          <step>D</step>
          <octave>4</octave>
          </pitch>
        <duration>2</duration>
        <voice>1</voice>
        <type>eighth</type>
        <stem>up</stem>
        <beam number="1">continue</beam>
        <lyric number="1">
          <syllabic>single</syllabic>
          <text font-family="Times New Roman" font-size="10.7317">in</text>
          </lyric>
        </note>
      <note default-x="226.58" default-y="-45.00">
        <pitch>
          <step>D</step>
          <octave>4</octave>
          </pitch>
        <duration>2</duration>
        <voice>1</voice>
        <type>eighth</type>
        <stem>up</stem>
        <beam number="1">end</beam>
        <lyric number="1">
          <syllabic>single</syllabic>
          <text font-family="Times New Roman" font-size="10.7317">a</text>
          </lyric>
        </note>
      </measure>
    <measure number="8" width="257.87">
      <harmony print-frame="no">
        <root>
          <root-step>C</root-step>
          </root>
        <kind>major</kind>
        </harmony>
      <note default-x="27.63" default-y="-50.00">
        <pitch>
          <step>C</step>
          <octave>4</octave>
          </pitch>
        <duration>3</duration>
        <voice>1</voice>
        <type>eighth</type>
        <dot/>
        <stem>up</stem>
        <beam number="1">begin</beam>
        <lyric number="1">
          <syllabic>single</syllabic>
          <text font-family="Times New Roman" font-size="10.7317">plum,</text>
          </lyric>
        </note>
      <note default-x="71.53" default-y="-15.00">
        <pitch>
          <step>C</step>
          <octave>5</octave>
          </pitch>
        <duration>1</duration>
        <tie type="start"/>
        <voice>1</voice>
        <type>16th</type>
        <stem>up</stem>
        <beam number="1">end</beam>
        <beam number="2">backward hook</beam>
        <notations>
          <tied type="start"/>
          </notations>
        </note>
      <note default-x="103.78" default-y="-15.00">
        <pitch>
          <step>C</step>
          <octave>5</octave>
          </pitch>
        <duration>3</duration>
        <tie type="stop"/>
        <voice>1</voice>
        <type>eighth</type>
        <dot/>
        <stem>down</stem>
        <beam number="1">begin</beam>
        <notations>
          <tied type="stop"/>
          </notations>
        <lyric number="1">
          <syllabic>single</syllabic>
          <text font-family="Times New Roman" font-size="10.7317">plum</text>
          </lyric>
        </note>
      <note default-x="151.67" default-y="-15.00">
        <pitch>
          <step>C</step>
          <octave>5</octave>
          </pitch>
        <duration>1</duration>
        <voice>1</voice>
        <type>16th</type>
        <stem>down</stem>
        <beam number="1">end</beam>
        <beam number="2">backward hook</beam>
        <lyric number="1">
          <syllabic>single</syllabic>
          <text font-family="Times New Roman" font-size="10.7317">plum.</text>
          </lyric>
        </note>
      <note>
        <rest/>
        <duration>8</duration>
        <voice>1</voice>
        <type>half</type>
        </note>
      <barline location="right">
        <bar-style>light-light</bar-style>
        </barline>
      </measure>
    <measure number="9" width="294.42">
      <print new-system="yes">
        <system-layout>
          <system-margins>
            <left-margin>0.00</left-margin>
            <right-margin>0.00</right-margin>
            </system-margins>
          <system-distance>150.00</system-distance>
          </system-layout>
        </print>
      <harmony print-frame="no">
        <root>
          <root-step>C</root-step>
          </root>
        <kind>major</kind>
        </harmony>
      <note default-x="65.17" default-y="-40.00">
        <pitch>
          <step>E</step>
          <octave>4</octave>
          </pitch>
        <duration>4</duration>
        <voice>1</voice>
        <type>quarter</type>
        <stem>up</stem>
        <lyric number="1">
          <syllabic>single</syllabic>
          <text font-family="Times New Roman" font-size="10.7317">Show</text>
          </lyric>
        </note>
      <note default-x="116.71" default-y="-40.00">
        <pitch>
          <step>E</step>
          <octave>4</octave>
          </pitch>
        <duration>2</duration>
        <voice>1</voice>
        <type>eighth</type>
        <stem>up</stem>
        <beam number="1">begin</beam>
        <lyric number="1">
          <syllabic>single</syllabic>
          <text font-family="Times New Roman" font-size="10.7317">me</text>
          </lyric>
        </note>
      <note default-x="152.93" default-y="-45.00">
        <pitch>
          <step>D</step>
          <octave>4</octave>
          </pitch>
        <duration>2</duration>
        <voice>1</voice>
        <type>eighth</type>
        <stem>up</stem>
        <beam number="1">end</beam>
        <lyric number="1">
          <syllabic>single</syllabic>
          <text font-family="Times New Roman" font-size="10.7317">your</text>
          </lyric>
        </note>
      <note default-x="189.75" default-y="-50.00">
        <pitch>
          <step>C</step>
          <octave>4</octave>
          </pitch>
        <duration>4</duration>
        <voice>1</voice>
        <type>quarter</type>
        <stem>up</stem>
        <lyric number="1">
          <syllabic>begin</syllabic>
          <text font-family="Times New Roman" font-size="10.7317">mo</text>
          </lyric>
        </note>
      <note default-x="241.29" default-y="-65.00">
        <pitch>
          <step>G</step>
          <octave>3</octave>
          </pitch>
        <duration>4</duration>
        <voice>1</voice>
        <type>quarter</type>
        <stem>up</stem>
        <lyric number="1">
          <syllabic>end</syllabic>
          <text font-family="Times New Roman" font-size="10.7317">tion,</text>
          </lyric>
        </note>
      </measure>
    <measure number="10" width="275.95">
      <note default-x="16.54" default-y="-40.00">
        <pitch>
          <step>E</step>
          <octave>4</octave>
          </pitch>
        <duration>3</duration>
        <voice>1</voice>
        <type>eighth</type>
        <dot/>
        <stem>up</stem>
        <beam number="1">begin</beam>
        <lyric number="1">
          <syllabic>begin</syllabic>
          <text font-family="Times New Roman" font-size="10.7317">tra</text>
          </lyric>
        </note>
      <note default-x="59.58" default-y="-45.00">
        <pitch>
          <step>D</step>
          <octave>4</octave>
          </pitch>
        <duration>1</duration>
        <voice>1</voice>
        <type>16th</type>
        <stem>up</stem>
        <beam number="1">end</beam>
        <beam number="2">backward hook</beam>
        <lyric number="1">
          <syllabic>middle</syllabic>
          <text font-family="Times New Roman" font-size="10.7317">la</text>
          </lyric>
        </note>
      <note default-x="81.64" default-y="-40.00">
        <pitch>
          <step>E</step>
          <octave>4</octave>
          </pitch>
        <duration>3</duration>
        <voice>1</voice>
        <type>eighth</type>
        <dot/>
        <stem>up</stem>
        <beam number="1">begin</beam>
        <lyric number="1">
          <syllabic>middle</syllabic>
          <text font-family="Times New Roman" font-size="10.7317">la</text>
          </lyric>
        </note>
      <note default-x="124.68" default-y="-35.00">
        <pitch>
          <step>F</step>
          <octave>4</octave>
          </pitch>
        <duration>1</duration>
        <voice>1</voice>
        <type>16th</type>
        <stem>up</stem>
        <beam number="1">end</beam>
        <beam number="2">backward hook</beam>
        <lyric number="1">
          <syllabic>middle</syllabic>
          <text font-family="Times New Roman" font-size="10.7317">la</text>
          </lyric>
        </note>
      <note default-x="146.75" default-y="-30.00">
        <pitch>
          <step>G</step>
          <octave>4</octave>
          </pitch>
        <duration>4</duration>
        <voice>1</voice>
        <type>quarter</type>
        <stem>up</stem>
        <lyric number="1">
          <syllabic>end</syllabic>
          <text font-family="Times New Roman" font-size="10.7317">la,</text>
          </lyric>
        </note>
      <note default-x="195.28" default-y="-50.00">
        <pitch>
          <step>C</step>
          <octave>4</octave>
          </pitch>
        <duration>2</duration>
        <voice>1</voice>
        <type>eighth</type>
        <stem>up</stem>
        <beam number="1">begin</beam>
        <lyric number="1">
          <syllabic>single</syllabic>
          <text font-family="Times New Roman" font-size="10.7317">Come</text>
          </lyric>
        </note>
      <note default-x="239.05" default-y="-50.00">
        <pitch>
          <step>C</step>
          <octave>4</octave>
          </pitch>
        <duration>2</duration>
        <voice>1</voice>
        <type>eighth</type>
        <stem>up</stem>
        <beam number="1">end</beam>
        <lyric number="1">
          <syllabic>single</syllabic>
          <text font-family="Times New Roman" font-size="10.7317">on,</text>
          </lyric>
        </note>
      </measure>
    <measure number="11" width="277.20">
      <harmony print-frame="no">
        <root>
          <root-step>G</root-step>
          </root>
        <kind>major</kind>
        </harmony>
      <note default-x="27.70" default-y="-45.00">
        <pitch>
          <step>D</step>
          <octave>4</octave>
          </pitch>
        <duration>4</duration>
        <voice>1</voice>
        <type>quarter</type>
        <stem>up</stem>
        <lyric number="1">
          <syllabic>single</syllabic>
          <text font-family="Times New Roman" font-size="10.7317">show</text>
          </lyric>
        </note>
      <note default-x="80.15" default-y="-45.00">
        <pitch>
          <step>D</step>
          <octave>4</octave>
          </pitch>
        <duration>2</duration>
        <voice>1</voice>
        <type>eighth</type>
        <stem>up</stem>
        <beam number="1">begin</beam>
        <lyric number="1">
          <syllabic>single</syllabic>
          <text font-family="Times New Roman" font-size="10.7317">me</text>
          </lyric>
        </note>
      <note default-x="116.37" default-y="-50.00">
        <pitch>
          <step>C</step>
          <octave>4</octave>
          </pitch>
        <duration>2</duration>
        <voice>1</voice>
        <type>eighth</type>
        <stem>up</stem>
        <beam number="1">end</beam>
        <lyric number="1">
          <syllabic>single</syllabic>
          <text font-family="Times New Roman" font-size="10.7317">your</text>
          </lyric>
        </note>
      <note default-x="154.29" default-y="-55.00">
        <pitch>
          <step>B</step>
          <octave>3</octave>
          </pitch>
        <duration>2</duration>
        <voice>1</voice>
        <type>eighth</type>
        <stem>up</stem>
        <beam number="1">begin</beam>
        <lyric number="1">
          <syllabic>begin</syllabic>
          <text font-family="Times New Roman" font-size="10.7317">mo</text>
          </lyric>
        </note>
      <note default-x="188.17" default-y="-60.00">
        <pitch>
          <step>A</step>
          <octave>3</octave>
          </pitch>
        <duration>2</duration>
        <voice>1</voice>
        <type>eighth</type>
        <stem>up</stem>
        <beam number="1">end</beam>
        <lyric number="1">
          <syllabic>end</syllabic>
          <text font-family="Times New Roman" font-size="10.7317">tion</text>
          </lyric>
        </note>
      <note default-x="223.15" default-y="-65.00">
        <pitch>
          <step>G</step>
          <octave>3</octave>
          </pitch>
        <duration>4</duration>
        <voice>1</voice>
        <type>quarter</type>
        <stem>up</stem>
        <lyric number="1">
          <syllabic>single</syllabic>
          <text font-family="Times New Roman" font-size="10.7317">la</text>
          </lyric>
        </note>
      </measure>
    <measure number="12" width="206.58">
      <note default-x="16.54" default-y="-30.00">
        <pitch>
          <step>G</step>
          <octave>4</octave>
          </pitch>
        <duration>6</duration>
        <voice>1</voice>
        <type>quarter</type>
        <dot/>
        <stem>up</stem>
        <lyric number="1">
          <syllabic>begin</syllabic>
          <text font-family="Times New Roman" font-size="10.7317">tra</text>
          </lyric>
        </note>
      <note default-x="68.44" default-y="-25.00">
        <pitch>
          <step>A</step>
          <octave>4</octave>
          </pitch>
        <duration>2</duration>
        <voice>1</voice>
        <type>eighth</type>
        <stem>up</stem>
        <lyric number="1">
          <syllabic>middle</syllabic>
          <text font-family="Times New Roman" font-size="10.7317">la</text>
          </lyric>
        </note>
      <note default-x="96.24" default-y="-30.00">
        <pitch>
          <step>G</step>
          <octave>4</octave>
          </pitch>
        <duration>2</duration>
        <voice>1</voice>
        <type>eighth</type>
        <stem>up</stem>
        <beam number="1">begin</beam>
        <lyric number="1">
          <syllabic>middle</syllabic>
          <text font-family="Times New Roman" font-size="10.7317">la</text>
          </lyric>
        </note>
      <note default-x="122.84" default-y="-35.00">
        <pitch>
          <step>F</step>
          <octave>4</octave>
          </pitch>
        <duration>2</duration>
        <voice>1</voice>
        <type>eighth</type>
        <stem>up</stem>
        <beam number="1">continue</beam>
        <lyric number="1">
          <syllabic>middle</syllabic>
          <text font-family="Times New Roman" font-size="10.7317">la</text>
          </lyric>
        </note>
      <note default-x="149.44" default-y="-40.00">
        <pitch>
          <step>E</step>
          <octave>4</octave>
          </pitch>
        <duration>2</duration>
        <voice>1</voice>
        <type>eighth</type>
        <stem>up</stem>
        <beam number="1">continue</beam>
        <lyric number="1">
          <syllabic>middle</syllabic>
          <text font-family="Times New Roman" font-size="10.7317">la</text>
          </lyric>
        </note>
      <note default-x="176.04" default-y="-45.00">
        <pitch>
          <step>D</step>
          <octave>4</octave>
          </pitch>
        <duration>2</duration>
        <voice>1</voice>
        <type>eighth</type>
        <stem>up</stem>
        <beam number="1">end</beam>
        <lyric number="1">
          <syllabic>end</syllabic>
          <text font-family="Times New Roman" font-size="10.7317">la,</text>
          </lyric>
        </note>
      </measure>
    <measure number="13" width="296.81">
      <print new-system="yes">
        <system-layout>
          <system-margins>
            <left-margin>0.00</left-margin>
            <right-margin>0.00</right-margin>
            </system-margins>
          <system-distance>150.00</system-distance>
          </system-layout>
        </print>
      <harmony print-frame="no">
        <root>
          <root-step>C</root-step>
          </root>
        <kind>major</kind>
        </harmony>
      <note default-x="65.17" default-y="-40.00">
        <pitch>
          <step>E</step>
          <octave>4</octave>
          </pitch>
        <duration>4</duration>
        <voice>1</voice>
        <type>quarter</type>
        <stem>up</stem>
        <lyric number="1">
          <syllabic>single</syllabic>
          <text font-family="Times New Roman" font-size="10.7317">Show</text>
          </lyric>
        </note>
      <note default-x="117.50" default-y="-40.00">
        <pitch>
          <step>E</step>
          <octave>4</octave>
          </pitch>
        <duration>2</duration>
        <voice>1</voice>
        <type>eighth</type>
        <stem>up</stem>
        <beam number="1">begin</beam>
        <lyric number="1">
          <syllabic>single</syllabic>
          <text font-family="Times New Roman" font-size="10.7317">me</text>
          </lyric>
        </note>
      <note default-x="153.72" default-y="-45.00">
        <pitch>
          <step>D</step>
          <octave>4</octave>
          </pitch>
        <duration>2</duration>
        <voice>1</voice>
        <type>eighth</type>
        <stem>up</stem>
        <beam number="1">end</beam>
        <lyric number="1">
          <syllabic>single</syllabic>
          <text font-family="Times New Roman" font-size="10.7317">your</text>
          </lyric>
        </note>
      <note default-x="190.54" default-y="-50.00">
        <pitch>
          <step>C</step>
          <octave>4</octave>
          </pitch>
        <duration>4</duration>
        <voice>1</voice>
        <type>quarter</type>
        <stem>up</stem>
        <lyric number="1">
          <syllabic>begin</syllabic>
          <text font-family="Times New Roman" font-size="10.7317">mo</text>
          </lyric>
        </note>
      <note default-x="242.87" default-y="-65.00">
        <pitch>
          <step>G</step>
          <octave>3</octave>
          </pitch>
        <duration>4</duration>
        <voice>1</voice>
        <type>quarter</type>
        <stem>up</stem>
        <lyric number="1">
          <syllabic>end</syllabic>
          <text font-family="Times New Roman" font-size="10.7317">tion,</text>
          </lyric>
        </note>
      </measure>
    <measure number="14" width="223.63">
      <note default-x="16.54" default-y="-40.00">
        <pitch>
          <step>E</step>
          <octave>4</octave>
          </pitch>
        <duration>3</duration>
        <voice>1</voice>
        <type>eighth</type>
        <dot/>
        <stem>up</stem>
        <beam number="1">begin</beam>
        <lyric number="1">
          <syllabic>begin</syllabic>
          <text font-family="Times New Roman" font-size="10.7317">tra</text>
          </lyric>
        </note>
      <note default-x="52.75" default-y="-45.00">
        <pitch>
          <step>D</step>
          <octave>4</octave>
          </pitch>
        <duration>1</duration>
        <voice>1</voice>
        <type>16th</type>
        <stem>up</stem>
        <beam number="1">end</beam>
        <beam number="2">backward hook</beam>
        <lyric number="1">
          <syllabic>middle</syllabic>
          <text font-family="Times New Roman" font-size="10.7317">la</text>
          </lyric>
        </note>
      <note default-x="71.97" default-y="-40.00">
        <pitch>
          <step>E</step>
          <octave>4</octave>
          </pitch>
        <duration>3</duration>
        <voice>1</voice>
        <type>eighth</type>
        <dot/>
        <stem>up</stem>
        <beam number="1">begin</beam>
        <lyric number="1">
          <syllabic>middle</syllabic>
          <text font-family="Times New Roman" font-size="10.7317">la</text>
          </lyric>
        </note>
      <note default-x="108.18" default-y="-35.00">
        <pitch>
          <step>F</step>
          <octave>4</octave>
          </pitch>
        <duration>1</duration>
        <voice>1</voice>
        <type>16th</type>
        <stem>up</stem>
        <beam number="1">end</beam>
        <beam number="2">backward hook</beam>
        <lyric number="1">
          <syllabic>end</syllabic>
          <text font-family="Times New Roman" font-size="10.7317">la,</text>
          </lyric>
        </note>
      <note default-x="140.36" default-y="-30.00">
        <pitch>
          <step>G</step>
          <octave>4</octave>
          </pitch>
        <duration>4</duration>
        <voice>1</voice>
        <type>quarter</type>
        <stem>up</stem>
        <lyric number="1">
          <syllabic>single</syllabic>
          <text font-family="Times New Roman" font-size="10.7317">She</text>
          </lyric>
        </note>
      <note default-x="181.20" default-y="-30.00">
        <pitch>
          <step>G</step>
          <octave>4</octave>
          </pitch>
        <duration>4</duration>
        <voice>1</voice>
        <type>quarter</type>
        <stem>up</stem>
        </note>
      </measure>
    <measure number="15" width="257.27">
      <note default-x="28.28" default-y="-15.00">
        <pitch>
          <step>C</step>
          <octave>5</octave>
          </pitch>
        <duration>4</duration>
        <voice>1</voice>
        <type>quarter</type>
        <stem>down</stem>
        <lyric number="1">
          <syllabic>single</syllabic>
          <text font-family="Times New Roman" font-size="10.7317">looks</text>
          </lyric>
        </note>
      <note default-x="76.15" default-y="-30.00">
        <pitch>
          <step>G</step>
          <octave>4</octave>
          </pitch>
        <duration>2</duration>
        <voice>1</voice>
        <type>eighth</type>
        <stem>up</stem>
        <beam number="1">begin</beam>
        <lyric number="1">
          <syllabic>single</syllabic>
          <text font-family="Times New Roman" font-size="10.7317">like</text>
          </lyric>
        </note>
      <note default-x="106.07" default-y="-30.00">
        <pitch>
          <step>G</step>
          <octave>4</octave>
          </pitch>
        <duration>2</duration>
        <voice>1</voice>
        <type>eighth</type>
        <stem>up</stem>
        <beam number="1">end</beam>
        <lyric number="1">
          <syllabic>single</syllabic>
          <text font-family="Times New Roman" font-size="10.7317">a</text>
          </lyric>
        </note>
      <note default-x="135.99" default-y="-40.00">
        <pitch>
          <step>E</step>
          <octave>4</octave>
          </pitch>
        <duration>2</duration>
        <voice>1</voice>
        <type>eighth</type>
        <stem>up</stem>
        <beam number="1">begin</beam>
        <lyric number="1">
          <syllabic>begin</syllabic>
          <text font-family="Times New Roman" font-size="10.7317">su</text>
          </lyric>
        </note>
      <note default-x="165.91" default-y="-40.00">
        <pitch>
          <step>E</step>
          <octave>4</octave>
          </pitch>
        <duration>2</duration>
        <voice>1</voice>
        <type>eighth</type>
        <stem>up</stem>
        <beam number="1">continue</beam>
        <lyric number="1">
          <syllabic>end</syllabic>
          <text font-family="Times New Roman" font-size="10.7317">gar</text>
          </lyric>
        </note>
      <note default-x="195.83" default-y="-45.00">
        <pitch>
          <step>D</step>
          <octave>4</octave>
          </pitch>
        <duration>2</duration>
        <voice>1</voice>
        <type>eighth</type>
        <stem>up</stem>
        <beam number="1">continue</beam>
        <lyric number="1">
          <syllabic>single</syllabic>
          <text font-family="Times New Roman" font-size="10.7317">in</text>
          </lyric>
        </note>
      <note default-x="225.75" default-y="-45.00">
        <pitch>
          <step>D</step>
          <octave>4</octave>
          </pitch>
        <duration>2</duration>
        <voice>1</voice>
        <type>eighth</type>
        <stem>up</stem>
        <beam number="1">end</beam>
        <lyric number="1">
          <syllabic>single</syllabic>
          <text font-family="Times New Roman" font-size="10.7317">a</text>
          </lyric>
        </note>
      </measure>
    <measure number="16" width="276.45">
      <note default-x="27.63" default-y="-50.00">
        <pitch>
          <step>C</step>
          <octave>4</octave>
          </pitch>
        <duration>3</duration>
        <voice>1</voice>
        <type>eighth</type>
        <dot/>
        <stem>up</stem>
        <beam number="1">begin</beam>
        <lyric number="1">
          <syllabic>single</syllabic>
          <text font-family="Times New Roman" font-size="10.7317">plum,</text>
          </lyric>
        </note>
      <note default-x="79.74" default-y="-15.00">
        <pitch>
          <step>C</step>
          <octave>5</octave>
          </pitch>
        <duration>1</duration>
        <tie type="start"/>
        <voice>1</voice>
        <type>16th</type>
        <stem>up</stem>
        <beam number="1">end</beam>
        <beam number="2">backward hook</beam>
        <notations>
          <tied type="start"/>
          </notations>
        <lyric number="1">
          <syllabic>single</syllabic>
          <text font-family="Times New Roman" font-size="10.7317">plum</text>
          </lyric>
        </note>
      <note default-x="121.60" default-y="-15.00">
        <pitch>
          <step>C</step>
          <octave>5</octave>
          </pitch>
        <duration>3</duration>
        <tie type="stop"/>
        <voice>1</voice>
        <type>eighth</type>
        <dot/>
        <stem>down</stem>
        <beam number="1">begin</beam>
        <notations>
          <tied type="stop"/>
          </notations>
        </note>
      <note default-x="167.45" default-y="-15.00">
        <pitch>
          <step>C</step>
          <octave>5</octave>
          </pitch>
        <duration>1</duration>
        <voice>1</voice>
        <type>16th</type>
        <stem>down</stem>
        <beam number="1">end</beam>
        <beam number="2">backward hook</beam>
        <lyric number="1">
          <syllabic>single</syllabic>
          <text font-family="Times New Roman" font-size="10.7317">plum.</text>
          </lyric>
        </note>
      <note>
        <rest/>
        <duration>8</duration>
        <voice>1</voice>
        <type>half</type>
        </note>
      <barline location="right">
        <bar-style>light-light</bar-style>
        </barline>
      </measure>
    <measure number="17" width="296.82">
      <print new-system="yes">
        <system-layout>
          <system-margins>
            <left-margin>0.00</left-margin>
            <right-margin>0.00</right-margin>
            </system-margins>
          <system-distance>150.00</system-distance>
          </system-layout>
        </print>
      <barline location="left">
        <bar-style>heavy-light</bar-style>
        <repeat direction="forward"/>
        </barline>
      <harmony print-frame="no">
        <root>
          <root-step>C</root-step>
          </root>
        <kind>major</kind>
        </harmony>
      <note default-x="72.98" default-y="-50.00">
        <pitch>
          <step>C</step>
          <octave>4</octave>
          </pitch>
        <duration>4</duration>
        <voice>1</voice>
        <type>quarter</type>
        <stem>up</stem>
        <lyric number="1">
          <syllabic>single</syllabic>
          <text font-family="Times New Roman" font-size="10.7317">All</text>
          </lyric>
        </note>
      <note default-x="128.54" default-y="-40.00">
        <pitch>
          <step>E</step>
          <octave>4</octave>
          </pitch>
        <duration>4</duration>
        <voice>1</voice>
        <type>quarter</type>
        <stem>up</stem>
        <lyric number="1">
          <syllabic>single</syllabic>
          <text font-family="Times New Roman" font-size="10.7317">had</text>
          </lyric>
        </note>
      <note default-x="184.10" default-y="-50.00">
        <pitch>
          <step>C</step>
          <octave>4</octave>
          </pitch>
        <duration>4</duration>
        <voice>1</voice>
        <type>quarter</type>
        <stem>up</stem>
        <lyric number="1">
          <syllabic>begin</syllabic>
          <text font-family="Times New Roman" font-size="10.7317">wa</text>
          </lyric>
        </note>
      <note default-x="239.66" default-y="-40.00">
        <pitch>
          <step>E</step>
          <octave>4</octave>
          </pitch>
        <duration>4</duration>
        <voice>1</voice>
        <type>quarter</type>
        <stem>up</stem>
        <lyric number="1">
          <syllabic>end</syllabic>
          <text font-family="Times New Roman" font-size="10.7317">ter</text>
          </lyric>
        </note>
      </measure>
    <measure number="18" width="218.04">
      <harmony print-frame="no">
        <root>
          <root-step>G</root-step>
          </root>
        <kind>major</kind>
        </harmony>
      <note default-x="19.49" default-y="-40.00">
        <pitch>
          <step>E</step>
          <octave>4</octave>
          </pitch>
        <duration>2</duration>
        <voice>1</voice>
        <type>eighth</type>
        <stem>up</stem>
        <beam number="1">begin</beam>
        <lyric number="1">
          <syllabic>single</syllabic>
          <text font-family="Times New Roman" font-size="10.7317">run</text>
          </lyric>
        </note>
      <note default-x="62.76" default-y="-45.00">
        <pitch>
          <step>D</step>
          <octave>4</octave>
          </pitch>
        <duration>2</duration>
        <tie type="start"/>
        <voice>1</voice>
        <type>eighth</type>
        <stem>up</stem>
        <beam number="1">end</beam>
        <notations>
          <tied type="start"/>
          </notations>
        <lyric number="1">
          <syllabic>single</syllabic>
          <text font-family="Times New Roman" font-size="10.7317">dry,</text>
          </lyric>
        </note>
      <note default-x="105.69" default-y="-45.00">
        <pitch>
          <step>D</step>
          <octave>4</octave>
          </pitch>
        <duration>12</duration>
        <tie type="stop"/>
        <voice>1</voice>
        <type>half</type>
        <dot/>
        <stem>up</stem>
        <notations>
          <tied type="stop"/>
          </notations>
        </note>
      </measure>
    <measure number="19" width="332.00">
      <note default-x="21.25" default-y="-45.00">
        <pitch>
          <step>D</step>
          <octave>4</octave>
          </pitch>
        <duration>4</duration>
        <voice>1</voice>
        <type>quarter</type>
        <stem>up</stem>
        <lyric number="1">
          <syllabic>single</syllabic>
          <text font-family="Times New Roman" font-size="10.7317">Got</text>
          </lyric>
        </note>
      <note default-x="93.14" default-y="-45.00">
        <pitch>
          <step>D</step>
          <octave>4</octave>
          </pitch>
        <duration>2</duration>
        <voice>1</voice>
        <type>eighth</type>
        <stem>up</stem>
        <beam number="1">begin</beam>
        <lyric number="1">
          <syllabic>single</syllabic>
          <text font-family="Times New Roman" font-size="10.7317">nowhere</text>
          </lyric>
        </note>
      <note default-x="141.67" default-y="-45.00">
        <pitch>
          <step>D</step>
          <octave>4</octave>
          </pitch>
        <duration>2</duration>
        <voice>1</voice>
        <type>eighth</type>
        <stem>up</stem>
        <beam number="1">end</beam>
        <lyric number="1">
          <syllabic>single</syllabic>
          <text font-family="Times New Roman" font-size="10.7317">to</text>
          </lyric>
        </note>
      <note default-x="186.61" default-y="-40.00">
        <pitch>
          <step>E</step>
          <octave>4</octave>
          </pitch>
        <duration>4</duration>
        <voice>1</voice>
        <type>quarter</type>
        <stem>up</stem>
        <lyric number="1">
          <syllabic>single</syllabic>
          <text font-family="Times New Roman" font-size="10.7317">wash</text>
          </lyric>
        </note>
      <note default-x="258.50" default-y="-45.00">
        <pitch>
          <step>D</step>
          <octave>4</octave>
          </pitch>
        <duration>4</duration>
        <voice>1</voice>
        <type>quarter</type>
        <stem>up</stem>
        <lyric number="1">
          <syllabic>single</syllabic>
          <text font-family="Times New Roman" font-size="10.7317">my</text>
          </lyric>
        </note>
      </measure>
    <measure number="20" width="207.28">
      <harmony print-frame="no">
        <root>
          <root-step>C</root-step>
          </root>
        <kind>major</kind>
        </harmony>
      <note default-x="32.52" default-y="-50.00">
        <pitch>
          <step>C</step>
          <octave>4</octave>
          </pitch>
        <duration>16</duration>
        <voice>1</voice>
        <type>whole</type>
        <lyric number="1">
          <syllabic>single</syllabic>
          <text font-family="Times New Roman" font-size="10.7317">clothes.</text>
          </lyric>
        </note>
      <barline location="right">
        <bar-style>light-heavy</bar-style>
        <repeat direction="backward"/>
        </barline>
      </measure>
    </part>
  </score-partwise>
